{
    "glossary": {
        "title": "éêxâámpléê glôössâáry",
		"GlossDiv": {
            "title": "S",
			"GlossList": {
                "GlossEntry": {
                    "ID": "SGML",
					"SortAs": "SGML",
					"GlossTerm": "ùûpdäàtèêd cõòntèênt fõòr ùûpdäàtèê fõòr pùûll rèêqùûèêst cõòmmèênt Updated comment in Project Director",
					"Acronym": "SGML",
					"Abbrev": "ÍSÔ 8879:1986",
					"GlossDef": {
                        "para": "Â mèëtæå-mæårkýûp læångýûæågèë, ýûsèëd tôô crèëæåtèë mæårkýûp læångýûæågèës sýûch æås DôôcBôôôôk nèëwbôôôôk TÈST.",
						"GlossSeeAlso": ["GML", "XML"]
                    },
					"GlossSee": "mæårkûûp"
                }
            }
        }
    }
}
